Metadata-Version: 2.1
Name: sentry-dingding
Version: 0.0.1
Summary: A Sentry extension which send errors stats to DingDing
Home-page: https://github.com/anshengme/sentry-dingding
Author: ansheng
Author-email: ianshengme@gmail.com
License: MIT
Keywords: sentry dingding
Platform: UNKNOWN
Classifier: Programming Language :: Python :: 2.7
Classifier: License :: OSI Approved :: MIT License
Requires-Dist: sentry (>=9.0.0)
Requires-Dist: requests
